{
  "GTO Wizard": "5yX0-0ZtGow",
  "Ken Berry MD": "hS88kOYoAtU",
  "Anthony Chaffee MD": "bCtJCOOEuv8",
  "Paul Saladino MD": "TR9--f5rgm8",
  "Joe Rogan": "wH2Nd8oHixo",
  "Nick Norwitz": "y7aQvXj0KfM",
  "GTO Lab": "klYWo8p_kGs",
  "Jared Alderman": "hzu7Y-jvtU0",
  "Thomas DeLauer": "_WextrGyY_0",
  "Lex Fridman": "nepKKz-MzFM",
  "Dr. Sten Ekberg": "0XFH6Hv3BTc",
  "Renaissance Periodization": "hd43ZXJ9WU4",
  "Peter Attia": "Tsqzx3L6UWs",
  "ModernWisdom": "zr_t_l5pimg",
  "Andrew Huberman": "cWCs7dxrt-A",
  "ThinkingPoker": "6w8amkDkeVw",
  "Ben Felix": "S9InNdQhFwc",
  "Mind The Game": "thfAiT7QF-w"
}